newwave/__init__.py
newwave/py.typed
newwave-0.1.1.dist-info/licenses/LICENSE.txt
newwave-0.1.1.dist-info/WHEEL
newwave-0.1.1.dist-info/METADATA
newwave-0.1.1.dist-info/RECORD
